django_svg_image_form_field/__init__.py
django_svg_image_form_field/svg_image_from_field.py
django_svg_image_form_field-1.0.1.dist-info/AUTHORS.rst
django_svg_image_form_field-1.0.1.dist-info/LICENSE
django_svg_image_form_field-1.0.1.dist-info/METADATA
django_svg_image_form_field-1.0.1.dist-info/WHEEL
django_svg_image_form_field-1.0.1.dist-info/top_level.txt
django_svg_image_form_field-1.0.1.dist-info/RECORD
