Metadata-Version: 1.1
Name: django-svg-image-form-field
Version: 1.0.1
Summary: A form field to handle validation of image + svg
Home-page: https://github.com/artrey/django-svg-image-form-field
Author: Alexander Ivanov
Author-email: oz.sasha.ivanov@gmail.com
License: MIT
Keywords: django,svg,image,form,field
Platform: UNKNOWN
Classifier: Development Status :: 5 - Production/Stable
Classifier: Framework :: Django :: 2.1
Classifier: Framework :: Django :: 2.2
Classifier: Framework :: Django :: 3.1
Classifier: Framework :: Django :: 3.2
Classifier: Intended Audience :: Developers
Classifier: License :: OSI Approved :: BSD License
Classifier: Natural Language :: English
Classifier: Programming Language :: Python :: 3
Classifier: Programming Language :: Python :: 3.6
Classifier: Programming Language :: Python :: 3.7
Classifier: Programming Language :: Python :: 3.8
Classifier: Programming Language :: Python :: 3.9
